pywc/__init__.py
pywc/__main__.py
pywc/main.py
ed_pywc-1.0.0.dist-info/LICENSE
ed_pywc-1.0.0.dist-info/METADATA
ed_pywc-1.0.0.dist-info/WHEEL
ed_pywc-1.0.0.dist-info/entry_points.txt
ed_pywc-1.0.0.dist-info/top_level.txt
ed_pywc-1.0.0.dist-info/RECORD
