Metadata-Version: 2.1
Name: ed-pywc
Version: 1.0.0
Summary: Python implementation of the UNIX wc (Word Count) utility
Home-page: https://github.com/edjchapman/pywc
Author: Ed Chapman
Author-email: ed@edchapman.co.uk
Keywords: cli tool wc word count
Classifier: Development Status :: 3 - Alpha
Classifier: Intended Audience :: Developers
Classifier: Topic :: Software Development :: Build Tools
Classifier: License :: OSI Approved :: MIT License
Classifier: Programming Language :: Python :: 3
Classifier: Programming Language :: Python :: 3.6
Classifier: Programming Language :: Python :: 3.7
Classifier: Programming Language :: Python :: 3.8
Classifier: Programming Language :: Python :: 3.9
Requires-Python: >=3.6
License-File: LICENSE
Requires-Dist: click >=8.0
Provides-Extra: dev
Requires-Dist: pytest >=7.0 ; extra == 'dev'
Requires-Dist: flake8 >=6.0 ; extra == 'dev'
Requires-Dist: isort >=5.12 ; extra == 'dev'
